{
  "generatedAt": "2026-07-24T14:38:06.640Z",
  "source": "betexplorer.com (Pinnacle / 1xBet odds)",
  "threshold": 1.6,
  "count": 24,
  "matches": [
    {
      "sport": "サッカー",
      "sportKey": "soccer",
      "league": "GEORGIA: GEORGIAN CUP",
      "home": "Margveti 2006",
      "away": "Iberia 1999",
      "favTeam": "Iberia 1999",
      "underTeam": "Margveti 2006",
      "favOdd": 1.02,
      "prob": 98,
      "book": "1xBet",
      "books": {
        "1xbet": 1.02
      },
      "avgFavOdd": 1.05,
      "time": "01:00",
      "kickoff": "2026-07-24T17:00:00+09:00",
      "niche": false,
      "url": "https://www.betexplorer.com/football/georgia/georgian-cup/margveti-2006-iberia-1999/pEpd0xRp/"
    },
    {
      "sport": "バレー",
      "sportKey": "volleyball",
      "league": "SOUTH AMERICA: COPA AMÉRICA WOMEN",
      "home": "Brazil U23 W",
      "away": "Chile W",
      "favTeam": "Brazil U23 W",
      "underTeam": "Chile W",
      "favOdd": 1.02,
      "prob": 98,
      "book": "1xBet",
      "books": {
        "1xbet": 1.02
      },
      "avgFavOdd": 1.07,
      "time": "04:00",
      "kickoff": "2026-07-24T20:00:00+09:00",
      "niche": true,
      "url": "https://www.betexplorer.com/volleyball/south-america/copa-america-women/brazil-chile/OjfhKDGk/"
    },
    {
      "sport": "アイスホッケー",
      "sportKey": "hockey",
      "league": "AUSTRALIA: AIHL",
      "home": "Melbourne Mustangs",
      "away": "Brisbane Lightning",
      "favTeam": "Melbourne Mustangs",
      "underTeam": "Brisbane Lightning",
      "favOdd": 1.03,
      "prob": 97,
      "book": "1xBet",
      "books": {
        "1xbet": 1.03
      },
      "avgFavOdd": 1.05,
      "time": "17:00",
      "kickoff": "2026-07-25T09:00:00+09:00",
      "niche": false,
      "url": "https://www.betexplorer.com/hockey/australia/aihl/melbourne-mustangs-brisbane-lightning/xhOFSzCs/"
    },
    {
      "sport": "バレー",
      "sportKey": "volleyball",
      "league": "SOUTH AMERICA: COPA AMÉRICA WOMEN",
      "home": "Venezuela W",
      "away": "Ecuador W",
      "favTeam": "Venezuela W",
      "underTeam": "Ecuador W",
      "favOdd": 1.04,
      "prob": 96,
      "book": "1xBet",
      "books": {
        "1xbet": 1.04
      },
      "avgFavOdd": 1.07,
      "time": "01:30",
      "kickoff": "2026-07-24T17:30:00+09:00",
      "niche": false,
      "url": "https://www.betexplorer.com/volleyball/south-america/copa-america-women/venezuela-ecuador/tUutVUU7/"
    },
    {
      "sport": "バレー",
      "sportKey": "volleyball",
      "league": "SOUTH AMERICA: COPA AMÉRICA WOMEN",
      "home": "Peru W",
      "away": "Bolivia W",
      "favTeam": "Peru W",
      "underTeam": "Bolivia W",
      "favOdd": 1.05,
      "prob": 95,
      "book": "1xBet",
      "books": {
        "1xbet": 1.05
      },
      "avgFavOdd": 1.12,
      "time": "09:00",
      "kickoff": "2026-07-25T01:00:00+09:00",
      "niche": false,
      "url": "https://www.betexplorer.com/volleyball/south-america/copa-america-women/peru-bolivia/WGc0Iio2/"
    },
    {
      "sport": "テニス",
      "sportKey": "tennis",
      "league": "ITF WOMEN - SINGLES: W100 AMSTETTEN, CLAY",
      "home": "Pastikova J.",
      "away": "Kostovic T.",
      "favTeam": "Kostovic T.",
      "underTeam": "Pastikova J.",
      "favOdd": 1.11,
      "prob": 90,
      "book": "1xBet",
      "books": {
        "1xbet": 1.11
      },
      "avgFavOdd": 1.11,
      "time": "00:30",
      "kickoff": "2026-07-24T16:30:00+09:00",
      "niche": true,
      "url": "https://www.betexplorer.com/tennis/itf-women-singles/w100-amstetten/pastikova-julie-kostovic-teodora/2P5zVx4o/"
    },
    {
      "sport": "アイスホッケー",
      "sportKey": "hockey",
      "league": "NEW ZEALAND: NZIHL",
      "home": "Southern Stampede",
      "away": "West Auckland Admirals",
      "favTeam": "Southern Stampede",
      "underTeam": "West Auckland Admirals",
      "favOdd": 1.13,
      "prob": 88,
      "book": "1xBet",
      "books": {
        "1xbet": 1.13
      },
      "avgFavOdd": 1.14,
      "time": "17:00",
      "kickoff": "2026-07-25T09:00:00+09:00",
      "niche": false,
      "url": "https://www.betexplorer.com/hockey/new-zealand/nzihl/southern-stampede-west-auckland-admirals/xOp9TEH7/"
    },
    {
      "sport": "テニス",
      "sportKey": "tennis",
      "league": "ITF MEN - SINGLES: M15 ROGNAC, HARD",
      "home": "Maxted L.",
      "away": "Lemire C.",
      "favTeam": "Maxted L.",
      "underTeam": "Lemire C.",
      "favOdd": 1.19,
      "prob": 84,
      "book": "1xBet",
      "books": {
        "1xbet": 1.19
      },
      "avgFavOdd": 1.18,
      "time": "00:30",
      "kickoff": "2026-07-24T16:30:00+09:00",
      "niche": true,
      "url": "https://www.betexplorer.com/tennis/itf-men-singles/m15-rognac/maxted-lui-lemire-clement/SzmgoIaQ/"
    },
    {
      "sport": "バレー",
      "sportKey": "volleyball",
      "league": "WORLD: NATIONS LEAGUE WOMEN",
      "home": "Brazil W",
      "away": "Italy W",
      "favTeam": "Italy W",
      "underTeam": "Brazil W",
      "favOdd": 1.19,
      "prob": 84,
      "book": "1xBet",
      "books": {
        "1xbet": 1.19
      },
      "avgFavOdd": 1.22,
      "time": "18:00",
      "kickoff": "2026-07-25T10:00:00+09:00",
      "niche": false,
      "url": "https://www.betexplorer.com/volleyball/world/nations-league-women/brazil-italy/jJsIQUeC/"
    },
    {
      "sport": "テニス",
      "sportKey": "tennis",
      "league": "ITF MEN - SINGLES: M25 SAO PAULO, CLAY",
      "home": "Rodriguez L. J.",
      "away": "Pereira J.",
      "favTeam": "Rodriguez L. J.",
      "underTeam": "Pereira J.",
      "favOdd": 1.23,
      "prob": 81,
      "book": "1xBet",
      "books": {
        "1xbet": 1.23
      },
      "avgFavOdd": 1.22,
      "time": "00:45",
      "kickoff": "2026-07-24T16:45:00+09:00",
      "niche": true,
      "url": "https://www.betexplorer.com/tennis/itf-men-singles/m25-sao-paulo/rodriguez-lorenzo-joaquin-pereira-jose/Q5B57sTd/"
    },
    {
      "sport": "テニス",
      "sportKey": "tennis",
      "league": "WTA - SINGLES: HAMBURG, CLAY",
      "home": "Korpatsch T.",
      "away": "Kalinina A.",
      "favTeam": "Kalinina A.",
      "underTeam": "Korpatsch T.",
      "favOdd": 1.3,
      "prob": 77,
      "book": "1xBet",
      "books": {
        "1xbet": 1.3
      },
      "avgFavOdd": 1.28,
      "time": "01:00",
      "kickoff": "2026-07-24T17:00:00+09:00",
      "niche": false,
      "url": "https://www.betexplorer.com/tennis/wta-singles/hamburg/korpatsch-tamara-kalinina-anhelina/02OxDgsJ/"
    },
    {
      "sport": "サッカー",
      "sportKey": "soccer",
      "league": "WORLD: CLUB FRIENDLY",
      "home": "Austria Vienna (Am)",
      "away": "Ried (Am)",
      "favTeam": "Austria Vienna (Am)",
      "underTeam": "Ried (Am)",
      "favOdd": 1.3,
      "prob": 77,
      "book": "1xBet",
      "books": {
        "1xbet": 1.3
      },
      "avgFavOdd": 1.33,
      "time": "01:00",
      "kickoff": "2026-07-24T17:00:00+09:00",
      "niche": false,
      "url": "https://www.betexplorer.com/football/world/club-friendly/austria-vienna-ried/tMLI9VU0/"
    },
    {
      "sport": "バレー",
      "sportKey": "volleyball",
      "league": "SOUTH AMERICA: COPA AMÉRICA WOMEN",
      "home": "Argentina W",
      "away": "Colombia W",
      "favTeam": "Argentina W",
      "underTeam": "Colombia W",
      "favOdd": 1.31,
      "prob": 76,
      "book": "1xBet",
      "books": {
        "1xbet": 1.31
      },
      "avgFavOdd": 1.37,
      "time": "06:30",
      "kickoff": "2026-07-24T22:30:00+09:00",
      "niche": false,
      "url": "https://www.betexplorer.com/volleyball/south-america/copa-america-women/argentina-colombia/nRSRhYME/"
    },
    {
      "sport": "テニス",
      "sportKey": "tennis",
      "league": "ITF MEN - SINGLES: M15 ROGNAC, HARD",
      "home": "Reco A.",
      "away": "Lestir L.",
      "favTeam": "Reco A.",
      "underTeam": "Lestir L.",
      "favOdd": 1.32,
      "prob": 76,
      "book": "1xBet",
      "books": {
        "1xbet": 1.32
      },
      "avgFavOdd": 1.3,
      "time": "00:30",
      "kickoff": "2026-07-24T16:30:00+09:00",
      "niche": true,
      "url": "https://www.betexplorer.com/tennis/itf-men-singles/m15-rognac/reco-alexandre-lestir-loan/Sve9EIoO/"
    },
    {
      "sport": "サッカー",
      "sportKey": "soccer",
      "league": "UZBEKISTAN: PRO LIGA",
      "home": "Olimpik-Mobiuz",
      "away": "TerDU",
      "favTeam": "Olimpik-Mobiuz",
      "underTeam": "TerDU",
      "favOdd": 1.33,
      "prob": 75,
      "book": "1xBet",
      "books": {
        "1xbet": 1.33
      },
      "avgFavOdd": 1.33,
      "time": "01:00",
      "kickoff": "2026-07-24T17:00:00+09:00",
      "niche": false,
      "url": "https://www.betexplorer.com/football/uzbekistan/pro-liga/olimpik-mobiuz-terdu/Wzrbk6D6/"
    },
    {
      "sport": "バスケ",
      "sportKey": "basketball",
      "league": "CANADA: CEBL",
      "home": "Scarborough Shooting Stars",
      "away": "Niagara River Lions",
      "favTeam": "Scarborough Shooting Stars",
      "underTeam": "Niagara River Lions",
      "favOdd": 1.34,
      "prob": 75,
      "book": "1xBet",
      "books": {
        "1xbet": 1.34
      },
      "avgFavOdd": 1.33,
      "time": "09:30",
      "kickoff": "2026-07-25T01:30:00+09:00",
      "niche": false,
      "url": "https://www.betexplorer.com/basketball/canada/cebl/scarborough-shooting-stars-niagara-river-lions/445hPt6c/"
    },
    {
      "sport": "バスケ",
      "sportKey": "basketball",
      "league": "MEXICO: LNBP",
      "home": "Abejas",
      "away": "Correcaminos",
      "favTeam": "Abejas",
      "underTeam": "Correcaminos",
      "favOdd": 1.35,
      "prob": 74,
      "book": "1xBet",
      "books": {
        "1xbet": 1.35
      },
      "avgFavOdd": 1.32,
      "time": "12:00",
      "kickoff": "2026-07-25T04:00:00+09:00",
      "niche": false,
      "url": "https://www.betexplorer.com/basketball/mexico/lnbp/abejas-correcaminos/0zUVp0Bb/"
    },
    {
      "sport": "野球",
      "sportKey": "baseball",
      "league": "USA: MLB",
      "home": "Detroit Tigers",
      "away": "Kansas City Royals",
      "favTeam": "Detroit Tigers",
      "underTeam": "Kansas City Royals",
      "favOdd": 1.36,
      "prob": 74,
      "book": "1xBet",
      "books": {
        "1xbet": 1.36
      },
      "avgFavOdd": 1.33,
      "time": "08:40",
      "kickoff": "2026-07-25T00:40:00+09:00",
      "niche": false,
      "url": "https://www.betexplorer.com/baseball/usa/mlb/detroit-tigers-kansas-city-royals/fcKpo2l4/"
    },
    {
      "sport": "野球",
      "sportKey": "baseball",
      "league": "USA: MLB",
      "home": "Milwaukee Brewers",
      "away": "Colorado Rockies",
      "favTeam": "Milwaukee Brewers",
      "underTeam": "Colorado Rockies",
      "favOdd": 1.4,
      "prob": 71,
      "book": "1xBet",
      "books": {
        "1xbet": 1.4
      },
      "avgFavOdd": 1.38,
      "time": "06:10",
      "kickoff": "2026-07-24T22:10:00+09:00",
      "niche": false,
      "url": "https://www.betexplorer.com/baseball/usa/mlb/milwaukee-brewers-colorado-rockies/raSkjlW0/"
    },
    {
      "sport": "バレー",
      "sportKey": "volleyball",
      "league": "WORLD: NATIONS LEAGUE WOMEN",
      "home": "China W",
      "away": "Turkey W",
      "favTeam": "Turkey W",
      "underTeam": "China W",
      "favOdd": 1.41,
      "prob": 71,
      "book": "1xBet",
      "books": {
        "1xbet": 1.41
      },
      "avgFavOdd": 1.4,
      "time": "21:30",
      "kickoff": "2026-07-25T13:30:00+09:00",
      "niche": false,
      "url": "https://www.betexplorer.com/volleyball/world/nations-league-women/china-turkey/8WqXVRnH/"
    },
    {
      "sport": "ハンドボール",
      "sportKey": "handball",
      "league": "WORLD: CLUB FRIENDLY",
      "home": "PLER",
      "away": "Dabas",
      "favTeam": "PLER",
      "underTeam": "Dabas",
      "favOdd": 1.42,
      "prob": 70,
      "book": "1xBet",
      "books": {
        "1xbet": 1.42
      },
      "avgFavOdd": 1.43,
      "time": "01:00",
      "kickoff": "2026-07-24T17:00:00+09:00",
      "niche": false,
      "url": "https://www.betexplorer.com/handball/world/club-friendly/pler-dabas-vse-kc/WvWYJYJE/"
    },
    {
      "sport": "野球",
      "sportKey": "baseball",
      "league": "CZECH REPUBLIC: EXTRALIGA",
      "home": "Eagles Prague",
      "away": "Draci Brno",
      "favTeam": "Draci Brno",
      "underTeam": "Eagles Prague",
      "favOdd": 1.44,
      "prob": 69,
      "book": "1xBet",
      "books": {
        "1xbet": 1.44
      },
      "avgFavOdd": 1.43,
      "time": "03:00",
      "kickoff": "2026-07-24T19:00:00+09:00",
      "niche": false,
      "url": "https://www.betexplorer.com/baseball/czech-republic/extraliga/eagles-prague-draci-brno/rcq7h8rn/"
    },
    {
      "sport": "テニス",
      "sportKey": "tennis",
      "league": "ITF MEN - DOUBLES: M25 OLLERSBACH, CLAY",
      "home": "Kumstat J. / Pecak S.",
      "away": "Motsnyy T. / Zakaria F.",
      "favTeam": "Kumstat J. / Pecak S.",
      "underTeam": "Motsnyy T. / Zakaria F.",
      "favOdd": 1.5,
      "prob": 67,
      "book": "1xBet",
      "books": {
        "1xbet": 1.5
      },
      "avgFavOdd": 1.5,
      "time": "01:00",
      "kickoff": "2026-07-24T17:00:00+09:00",
      "niche": true,
      "url": "https://www.betexplorer.com/tennis/itf-men-doubles/m25-ollersbach/kumstat-jan-pecak-stepan-motsnyy-taras-zakaria-faria/Uuklwc2r/"
    },
    {
      "sport": "サッカー",
      "sportKey": "soccer",
      "league": "WORLD: CLUB FRIENDLY",
      "home": "Eyupspor",
      "away": "Istanbulspor AS",
      "favTeam": "Eyupspor",
      "underTeam": "Istanbulspor AS",
      "favOdd": 1.51,
      "prob": 66,
      "book": "1xBet",
      "books": {
        "1xbet": 1.51
      },
      "avgFavOdd": 1.5,
      "time": "01:00",
      "kickoff": "2026-07-24T17:00:00+09:00",
      "niche": false,
      "url": "https://www.betexplorer.com/football/world/club-friendly/eyupspor-istanbulspor-as/QLXHML4J/"
    }
  ]
}